pyhdpowerview
pypowerview
