Metadata-Version: 2.1
Name: pyhdpowerview
Version: 0.0.8
Summary: Python API for talking to Powerview Hub
Home-page: https://github.com/safepay/pyhdpowerview
Author: Richard Mann
Author-email: mannrj@outlook.com
License: UNKNOWN
Platform: UNKNOWN
Classifier: Programming Language :: Python :: 3.6
Classifier: License :: OSI Approved :: MIT License
Classifier: Operating System :: OS Independent
Classifier: Development Status :: 4 - Beta
